learn4free/__init__.py
learn4free/scraper.py
learn4free-1.0.0.dist-info/licenses/LICENSE
learn4free-1.0.0.dist-info/METADATA
learn4free-1.0.0.dist-info/WHEEL
learn4free-1.0.0.dist-info/entry_points.txt
learn4free-1.0.0.dist-info/top_level.txt
learn4free-1.0.0.dist-info/RECORD
