Metadata-Version: 2.4
Name: learn4free
Version: 1.0.0
Summary: A scraper for free courses from coursekingdom.xyz
Home-page: https://github.com/Aether-0/learn4free
Author: Aether
Author-email: sanwana12.conceptx@gmail.com
Classifier: Programming Language :: Python :: 3
Classifier: License :: OSI Approved :: MIT License
Classifier: Operating System :: OS Independent
Requires-Python: >=3.6
License-File: LICENSE
Requires-Dist: requests
Requires-Dist: beautifulsoup4
Requires-Dist: fake-useragent
Requires-Dist: rich
Dynamic: author
Dynamic: author-email
Dynamic: classifier
Dynamic: description
Dynamic: description-content-type
Dynamic: home-page
Dynamic: license-file
Dynamic: requires-dist
Dynamic: requires-python
Dynamic: summary
